{
  "movie_name": "еү§еңәзүҲ BAN G DREAM! Episode of Roselia I: Promise",
  "jp_name": "еҠҮе ҙзүҲ пјўпҪҒпҪҺпј§ пјӨпҪ’пҪ…пҪҒпҪҚпјҒ пјҘпҪҗпҪүпҪ“пҪҸпҪ„пҪ… пҪҸпҪҶ пјІпҪҸпҪ“пҪ…пҪҢпҪүпҪҒ пј©пјҡзҙ„жқҹ",
  "releaseDate": "24-04-2021",
  "entries": [
    {
      "title": "Including Independents",
      "date": "24-04-2021",
      "time": "7PM",
      "rank": 4,
      "sales": 9520,
      "seats": 52973,
      "showtimes": 367,
      "theaters": 102,
      "last_week_ratio": null,
      "day": "1st Sat"
    },
    {
      "title": "Including Independents",
      "date": "24-04-2021",
      "time": "2PM",
      "rank": 4,
      "sales": 5893,
      "seats": 32367,
      "showtimes": 227,
      "theaters": 102,
      "last_week_ratio": null,
      "day": "1st Sat"
    },
    {
      "title": "Including Independents",
      "date": "24-04-2021",
      "time": "Final",
      "rank": 4,
      "sales": 7132,
      "seats": 61372,
      "showtimes": 417,
      "theaters": 92,
      "last_week_ratio": null,
      "day": "1st Sat"
    },
    {
      "title": "Including Independents",
      "date": "26-04-2021",
      "time": "7PM",
      "rank": 5,
      "sales": 1092,
      "seats": 37377,
      "showtimes": 260,
      "theaters": 83,
      "last_week_ratio": null,
      "day": "1st Mon"
    },
    {
      "title": "Including Independents",
      "date": "26-04-2021",
      "time": "2PM",
      "rank": 5,
      "sales": 685,
      "seats": 22188,
      "showtimes": 150,
      "theaters": 83,
      "last_week_ratio": null,
      "day": "1st Mon"
    },
    {
      "title": "Including Independents",
      "date": "26-04-2021",
      "time": "Final",
      "rank": 4,
      "sales": 5185,
      "seats": 45468,
      "showtimes": 323,
      "theaters": 85,
      "last_week_ratio": null,
      "day": "1st Mon"
    },
    {
      "title": "Including Independents",
      "date": "27-04-2021",
      "time": "7PM",
      "rank": 7,
      "sales": 775,
      "seats": 37107,
      "showtimes": 254,
      "theaters": 73,
      "last_week_ratio": null,
      "day": "1st Tue"
    },
    {
      "title": "Including Independents",
      "date": "27-04-2021",
      "time": "2PM",
      "rank": 7,
      "sales": 425,
      "seats": 22093,
      "showtimes": 148,
      "theaters": 73,
      "last_week_ratio": null,
      "day": "1st Tue"
    },
    {
      "title": "Including Independents",
      "date": "27-04-2021",
      "time": "Final",
      "rank": 5,
      "sales": 1295,
      "seats": 44553,
      "showtimes": 311,
      "theaters": 83,
      "last_week_ratio": null,
      "day": "1st Tue"
    },
    {
      "title": "Including Independents",
      "date": "04-05-2021",
      "time": "7PM",
      "rank": 11,
      "sales": 1613,
      "seats": 24793,
      "showtimes": 190,
      "theaters": 79,
      "last_week_ratio": 208.1,
      "day": "2nd Tue"
    },
    {
      "title": "Including Independents",
      "date": "04-05-2021",
      "time": "2PM",
      "rank": 12,
      "sales": 1017,
      "seats": 13594,
      "showtimes": 103,
      "theaters": 79,
      "last_week_ratio": 239.3,
      "day": "2nd Tue"
    },
    {
      "title": "Including Independents",
      "date": "04-05-2021",
      "time": "Final",
      "rank": 11,
      "sales": 2126,
      "seats": 30099,
      "showtimes": 230,
      "theaters": 74,
      "last_week_ratio": 164.2,
      "day": "2nd Tue"
    },
    {
      "title": "Including Independents",
      "date": "09-05-2021",
      "time": "7PM",
      "rank": 11,
      "sales": 1222,
      "seats": 17176,
      "showtimes": 134,
      "theaters": 79,
      "last_week_ratio": null,
      "day": "3rd Sun"
    },
    {
      "title": "Including Independents",
      "date": "09-05-2021",
      "time": "2PM",
      "rank": 9,
      "sales": 702,
      "seats": 9360,
      "showtimes": 74,
      "theaters": 79,
      "last_week_ratio": null,
      "day": "3rd Sun"
    },
    {
      "title": "Including Independents",
      "date": "09-05-2021",
      "time": "Final",
      "rank": 7,
      "sales": 2378,
      "seats": 21726,
      "showtimes": 166,
      "theaters": 79,
      "last_week_ratio": null,
      "day": "3rd Sun"
    },
    {
      "title": "Including Independents",
      "date": "10-05-2021",
      "time": "7PM",
      "rank": 9,
      "sales": 445,
      "seats": 18507,
      "showtimes": 141,
      "theaters": 79,
      "last_week_ratio": null,
      "day": "3rd Mon"
    },
    {
      "title": "Including Independents",
      "date": "10-05-2021",
      "time": "2PM",
      "rank": 13,
      "sales": 201,
      "seats": 9730,
      "showtimes": 76,
      "theaters": 79,
      "last_week_ratio": null,
      "day": "3rd Mon"
    },
    {
      "title": "Including Independents",
      "date": "10-05-2021",
      "time": "Final",
      "rank": 11,
      "sales": 1336,
      "seats": 20526,
      "showtimes": 160,
      "theaters": 79,
      "last_week_ratio": null,
      "day": "3rd Mon"
    },
    {
      "title": "Including Independents",
      "date": "14-05-2021",
      "time": "7PM",
      "rank": 15,
      "sales": 792,
      "seats": 21570,
      "showtimes": 155,
      "theaters": 87,
      "last_week_ratio": null,
      "day": "3rd Fri"
    },
    {
      "title": "Including Independents",
      "date": "14-05-2021",
      "time": "2PM",
      "rank": 17,
      "sales": 262,
      "seats": 9378,
      "showtimes": 73,
      "theaters": 87,
      "last_week_ratio": null,
      "day": "3rd Fri"
    },
    {
      "title": "Including Independents",
      "date": "14-05-2021",
      "time": "Final",
      "rank": 19,
      "sales": 316,
      "seats": 18432,
      "showtimes": 154,
      "theaters": 83,
      "last_week_ratio": null,
      "day": "3rd Fri"
    },
    {
      "title": "Including Independents",
      "date": "21-05-2021",
      "time": "7PM",
      "rank": 23,
      "sales": 308,
      "seats": 12508,
      "showtimes": 92,
      "theaters": 83,
      "last_week_ratio": null,
      "day": "4th Fri"
    },
    {
      "title": "Including Independents",
      "date": "21-05-2021",
      "time": "Final",
      "rank": 23,
      "sales": 376,
      "seats": 18685,
      "showtimes": 146,
      "theaters": 85,
      "last_week_ratio": 119,
      "day": "4th Fri"
    }
  ]
}