{
  "movie_name": "Long Walk",
  "jp_name": "ロングウォーク",
  "releaseDate": "26-06-2026",
  "entries": [
    {
      "title": "Including Independents",
      "date": "26-06-2026",
      "time": "2PM",
      "rank": 15,
      "sales": 1237,
      "seats": 14763,
      "showtimes": 111,
      "theaters": 101,
      "last_week_ratio": null,
      "day": "1st Fri"
    },
    {
      "title": "Including Independents",
      "date": "26-06-2026",
      "time": "7PM",
      "rank": 16,
      "sales": 2313,
      "seats": 26585,
      "showtimes": 202,
      "theaters": 101,
      "last_week_ratio": null,
      "day": "1st Fri"
    },
    {
      "title": "Including Independents",
      "date": "26-06-2026",
      "time": "Final",
      "rank": 13,
      "sales": 3311,
      "seats": 38284,
      "showtimes": 289,
      "theaters": 101,
      "last_week_ratio": null,
      "day": "1st Fri"
    },
    {
      "title": "Including Independents",
      "date": "27-06-2026",
      "time": "2PM",
      "rank": 16,
      "sales": 1980,
      "seats": 14137,
      "showtimes": 113,
      "theaters": 111,
      "last_week_ratio": null,
      "day": "1st Sat"
    },
    {
      "title": "Including Independents",
      "date": "27-06-2026",
      "time": "7PM",
      "rank": 16,
      "sales": 3766,
      "seats": 26829,
      "showtimes": 207,
      "theaters": 111,
      "last_week_ratio": null,
      "day": "1st Sat"
    },
    {
      "title": "Including Independents",
      "date": "27-06-2026",
      "time": "Final",
      "rank": 15,
      "sales": 4971,
      "seats": 39602,
      "showtimes": 303,
      "theaters": 111,
      "last_week_ratio": null,
      "day": "1st Sat"
    },
    {
      "title": "Including Independents",
      "date": "28-06-2026",
      "time": "2PM",
      "rank": 16,
      "sales": 2383,
      "seats": 14780,
      "showtimes": 117,
      "theaters": 111,
      "last_week_ratio": null,
      "day": "1st Sun"
    },
    {
      "title": "Including Independents",
      "date": "28-06-2026",
      "time": "7PM",
      "rank": 16,
      "sales": 3932,
      "seats": 26968,
      "showtimes": 208,
      "theaters": 111,
      "last_week_ratio": null,
      "day": "1st Sun"
    },
    {
      "title": "Including Independents",
      "date": "28-06-2026",
      "time": "Final",
      "rank": 16,
      "sales": 4614,
      "seats": 39988,
      "showtimes": 305,
      "theaters": 111,
      "last_week_ratio": null,
      "day": "1st Sun"
    },
    {
      "title": "Including Independents",
      "date": "29-06-2026",
      "time": "2PM",
      "rank": 14,
      "sales": 1245,
      "seats": 15131,
      "showtimes": 117,
      "theaters": 111,
      "last_week_ratio": null,
      "day": "1st Mon"
    },
    {
      "title": "Including Independents",
      "date": "29-06-2026",
      "time": "7PM",
      "rank": 14,
      "sales": 2075,
      "seats": 27749,
      "showtimes": 214,
      "theaters": 111,
      "last_week_ratio": null,
      "day": "1st Mon"
    },
    {
      "title": "Including Independents",
      "date": "29-06-2026",
      "time": "Final",
      "rank": 14,
      "sales": 2552,
      "seats": 39948,
      "showtimes": 309,
      "theaters": 111,
      "last_week_ratio": null,
      "day": "1st Mon"
    },
    {
      "title": "Including Independents",
      "date": "30-06-2026",
      "time": "2PM",
      "rank": 13,
      "sales": 917,
      "seats": 14943,
      "showtimes": 115,
      "theaters": 111,
      "last_week_ratio": null,
      "day": "1st Tue"
    },
    {
      "title": "Including Independents",
      "date": "30-06-2026",
      "time": "7PM",
      "rank": 14,
      "sales": 1635,
      "seats": 27895,
      "showtimes": 215,
      "theaters": 111,
      "last_week_ratio": null,
      "day": "1st Tue"
    },
    {
      "title": "Including Independents",
      "date": "30-06-2026",
      "time": "Final",
      "rank": 14,
      "sales": 2095,
      "seats": 39629,
      "showtimes": 305,
      "theaters": 111,
      "last_week_ratio": null,
      "day": "1st Tue"
    },
    {
      "title": "Including Independents",
      "date": "01-07-2026",
      "time": "2PM",
      "rank": 13,
      "sales": 1309,
      "seats": 15021,
      "showtimes": 115,
      "theaters": 111,
      "last_week_ratio": null,
      "day": "1st Wed"
    },
    {
      "title": "Including Independents",
      "date": "01-07-2026",
      "time": "7PM",
      "rank": 14,
      "sales": 2371,
      "seats": 27968,
      "showtimes": 215,
      "theaters": 111,
      "last_week_ratio": null,
      "day": "1st Wed"
    },
    {
      "title": "Including Independents",
      "date": "01-07-2026",
      "time": "Final",
      "rank": 13,
      "sales": 2986,
      "seats": 39625,
      "showtimes": 304,
      "theaters": 111,
      "last_week_ratio": null,
      "day": "1st Wed"
    },
    {
      "title": "Including Independents",
      "date": "02-07-2026",
      "time": "2PM",
      "rank": 12,
      "sales": 884,
      "seats": 14923,
      "showtimes": 114,
      "theaters": 111,
      "last_week_ratio": null,
      "day": "1st Thu"
    },
    {
      "title": "Including Independents",
      "date": "02-07-2026",
      "time": "7PM",
      "rank": 13,
      "sales": 1578,
      "seats": 27874,
      "showtimes": 214,
      "theaters": 111,
      "last_week_ratio": null,
      "day": "1st Thu"
    },
    {
      "title": "Including Independents",
      "date": "02-07-2026",
      "time": "Final",
      "rank": 13,
      "sales": 1992,
      "seats": 39309,
      "showtimes": 301,
      "theaters": 111,
      "last_week_ratio": null,
      "day": "1st Thu"
    },
    {
      "title": "Including Independents",
      "date": "03-07-2026",
      "time": "7PM",
      "rank": 24,
      "sales": 746,
      "seats": 9160,
      "showtimes": 77,
      "theaters": 100,
      "last_week_ratio": null,
      "day": "2nd Fri"
    },
    {
      "title": "Including Independents",
      "date": "03-07-2026",
      "time": "Final",
      "rank": 23,
      "sales": 1104,
      "seats": 12977,
      "showtimes": 110,
      "theaters": 100,
      "last_week_ratio": null,
      "day": "2nd Fri"
    },
    {
      "title": "Including Independents",
      "date": "06-07-2026",
      "time": "7PM",
      "rank": 24,
      "sales": 585,
      "seats": 8618,
      "showtimes": 73,
      "theaters": 99,
      "last_week_ratio": null,
      "day": "2nd Mon"
    },
    {
      "title": "Including Independents",
      "date": "06-07-2026",
      "time": "Final",
      "rank": 24,
      "sales": 775,
      "seats": 13767,
      "showtimes": 116,
      "theaters": 99,
      "last_week_ratio": null,
      "day": "2nd Mon"
    },
    {
      "title": "Including Independents",
      "date": "07-07-2026",
      "time": "7PM",
      "rank": 23,
      "sales": 527,
      "seats": 8521,
      "showtimes": 72,
      "theaters": 99,
      "last_week_ratio": null,
      "day": "2nd Tue"
    },
    {
      "title": "Including Independents",
      "date": "07-07-2026",
      "time": "Final",
      "rank": 24,
      "sales": 742,
      "seats": 13726,
      "showtimes": 115,
      "theaters": 99,
      "last_week_ratio": null,
      "day": "2nd Tue"
    },
    {
      "title": "Including Independents",
      "date": "08-07-2026",
      "time": "7PM",
      "rank": 24,
      "sales": 679,
      "seats": 8604,
      "showtimes": 72,
      "theaters": 99,
      "last_week_ratio": null,
      "day": "2nd Wed"
    },
    {
      "title": "Including Independents",
      "date": "08-07-2026",
      "time": "Final",
      "rank": 24,
      "sales": 965,
      "seats": 13869,
      "showtimes": 116,
      "theaters": 99,
      "last_week_ratio": null,
      "day": "2nd Wed"
    },
    {
      "title": "Including Independents",
      "date": "09-07-2026",
      "time": "7PM",
      "rank": 25,
      "sales": 516,
      "seats": 8788,
      "showtimes": 70,
      "theaters": 98,
      "last_week_ratio": null,
      "day": "2nd Thu"
    }
  ]
}