{
  "movie_name": "Movie Doraemon: Nobita's New Underwater Ghost Castle",
  "jp_name": "映画ドラえもん 新・のび太の海底鬼岩城",
  "releaseDate": "10-04-2026",
  "entries": [
    {
      "title": "Including Independents",
      "date": "10-04-2026",
      "time": "7PM",
      "rank": 6,
      "sales": 3975,
      "seats": 72331,
      "showtimes": 524,
      "theaters": 266,
      "last_week_ratio": null,
      "day": "1st Fri"
    },
    {
      "title": "Including Independents",
      "date": "10-04-2026",
      "time": "Final",
      "rank": 4,
      "sales": 7600,
      "seats": 254050,
      "showtimes": 916,
      "theaters": 271,
      "last_week_ratio": null,
      "day": "1st Fri"
    },
    {
      "title": "Including Independents",
      "date": "11-04-2026",
      "time": "7PM",
      "rank": 2,
      "sales": 20847,
      "seats": 84942,
      "showtimes": 619,
      "theaters": 266,
      "last_week_ratio": null,
      "day": "1st Sat"
    },
    {
      "title": "Including Independents",
      "date": "11-04-2026",
      "time": "Final",
      "rank": 7,
      "sales": 3982,
      "seats": 72487,
      "showtimes": 525,
      "theaters": 266,
      "last_week_ratio": null,
      "day": "1st Sat"
    },
    {
      "title": "Including Independents",
      "date": "20-04-2026",
      "time": "7PM",
      "rank": 8,
      "sales": 2437,
      "seats": 50406,
      "showtimes": 394,
      "theaters": 262,
      "last_week_ratio": 114.1,
      "day": "2nd Mon"
    },
    {
      "title": "Including Independents",
      "date": "20-04-2026",
      "time": "2PM",
      "rank": 6,
      "sales": 1898,
      "seats": 37679,
      "showtimes": 294,
      "theaters": 262,
      "last_week_ratio": 130.8,
      "day": "2nd Mon"
    },
    {
      "title": "Including Independents",
      "date": "20-04-2026",
      "time": "Final",
      "rank": 3,
      "sales": 24784,
      "seats": 78043,
      "showtimes": 601,
      "theaters": 266,
      "last_week_ratio": null,
      "day": "2nd Mon"
    }
  ]
}