{
  "movie_name": "Movie version of *Uta no☆Prince-sama♪* Maji LOVE Kingdom",
  "jp_name": "劇場版 うたの☆プリンスさまっ♪ マジＬＯＶＥキングダム",
  "releaseDate": "14-07-2019",
  "entries": [
    {
      "title": "Including Independents",
      "date": "14-07-2019",
      "time": "7PM",
      "rank": 10,
      "sales": 11389,
      "seats": 21807,
      "showtimes": 140,
      "theaters": 119,
      "last_week_ratio": null,
      "day": "1st Sun"
    },
    {
      "title": "Including Independents",
      "date": "14-07-2019",
      "time": "2PM",
      "rank": 8,
      "sales": 6604,
      "seats": 11515,
      "showtimes": 73,
      "theaters": 119,
      "last_week_ratio": null,
      "day": "1st Sun"
    },
    {
      "title": "Including Independents",
      "date": "15-07-2019",
      "time": "7PM",
      "rank": 9,
      "sales": 8742,
      "seats": 25990,
      "showtimes": 166,
      "theaters": 119,
      "last_week_ratio": 126.3,
      "day": "1st Mon"
    },
    {
      "title": "Including Independents",
      "date": "15-07-2019",
      "time": "2PM",
      "rank": 9,
      "sales": 4848,
      "seats": 12090,
      "showtimes": 74,
      "theaters": 119,
      "last_week_ratio": 182.1,
      "day": "1st Mon"
    }
  ]
}