{
  "movie_name": "Sorry about my brothers",
  "jp_name": "うちの弟どもがすみません",
  "releaseDate": "23-12-2024",
  "entries": [
    {
      "title": "Including Independents",
      "date": "23-12-2024",
      "time": "7PM",
      "rank": 14,
      "sales": 906,
      "seats": 18883,
      "showtimes": 157,
      "theaters": 154,
      "last_week_ratio": null,
      "day": "1st Mon"
    },
    {
      "title": "Including Independents",
      "date": "23-12-2024",
      "time": "2PM",
      "rank": 12,
      "sales": 331,
      "seats": 9508,
      "showtimes": 74,
      "theaters": 154,
      "last_week_ratio": null,
      "day": "1st Mon"
    },
    {
      "title": "Including Independents",
      "date": "23-12-2024",
      "time": "Final",
      "rank": 15,
      "sales": 2102,
      "seats": 21292,
      "showtimes": 164,
      "theaters": 143,
      "last_week_ratio": null,
      "day": "1st Mon"
    },
    {
      "title": "Including Independents",
      "date": "26-12-2024",
      "time": "7PM",
      "rank": 12,
      "sales": 1599,
      "seats": 18887,
      "showtimes": 151,
      "theaters": 152,
      "last_week_ratio": null,
      "day": "1st Thu"
    },
    {
      "title": "Including Independents",
      "date": "26-12-2024",
      "time": "2PM",
      "rank": 11,
      "sales": 621,
      "seats": 9424,
      "showtimes": 71,
      "theaters": 152,
      "last_week_ratio": null,
      "day": "1st Thu"
    },
    {
      "title": "Including Independents",
      "date": "26-12-2024",
      "time": "Final",
      "rank": 15,
      "sales": 1576,
      "seats": 21562,
      "showtimes": 164,
      "theaters": 148,
      "last_week_ratio": null,
      "day": "1st Thu"
    },
    {
      "title": "Including Independents",
      "date": "31-12-2024",
      "time": "7PM",
      "rank": 24,
      "sales": 573,
      "seats": 14291,
      "showtimes": 99,
      "theaters": 132,
      "last_week_ratio": null,
      "day": "2nd Tue"
    },
    {
      "title": "Including Independents",
      "date": "31-12-2024",
      "time": "2PM",
      "rank": 24,
      "sales": 335,
      "seats": 6593,
      "showtimes": 45,
      "theaters": 132,
      "last_week_ratio": null,
      "day": "2nd Tue"
    },
    {
      "title": "Including Independents",
      "date": "31-12-2024",
      "time": "Final",
      "rank": 22,
      "sales": 1294,
      "seats": 18150,
      "showtimes": 123,
      "theaters": 127,
      "last_week_ratio": 127.6,
      "day": "2nd Tue"
    }
  ]
}