{
  "movie_name": "Spider's Castle",
  "jp_name": "蜘蛛巣城",
  "releaseDate": "19-11-2022",
  "entries": [
    {
      "title": "Including Independents",
      "date": "19-11-2022",
      "time": "2PM",
      "rank": 22,
      "sales": 341,
      "seats": 2075,
      "showtimes": 18,
      "theaters": 19,
      "last_week_ratio": null,
      "day": "1st Sat"
    },
    {
      "title": "Including Independents",
      "date": "21-11-2022",
      "time": "2PM",
      "rank": 25,
      "sales": 130,
      "seats": 1897,
      "showtimes": 17,
      "theaters": 19,
      "last_week_ratio": null,
      "day": "1st Mon"
    },
    {
      "title": "Including Independents",
      "date": "03-12-2022",
      "time": "2PM",
      "rank": 24,
      "sales": 328,
      "seats": 2237,
      "showtimes": 19,
      "theaters": 20,
      "last_week_ratio": 159.2,
      "day": "3rd Sat"
    },
    {
      "title": "Including Independents",
      "date": "07-12-2022",
      "time": "2PM",
      "rank": 24,
      "sales": 223,
      "seats": 2181,
      "showtimes": 20,
      "theaters": 20,
      "last_week_ratio": 174.2,
      "day": "3rd Wed"
    },
    {
      "title": "Including Independents",
      "date": "12-12-2022",
      "time": "2PM",
      "rank": 25,
      "sales": 129,
      "seats": 2164,
      "showtimes": 20,
      "theaters": 20,
      "last_week_ratio": null,
      "day": "4th Mon"
    }
  ]
}