{
  "movie_name": "The song you left last",
  "jp_name": "君が最後に遺した歌",
  "releaseDate": "26-03-2026",
  "entries": [
    {
      "title": "Including Independents",
      "date": "26-03-2026",
      "time": "7PM",
      "rank": 7,
      "sales": 13066,
      "seats": 203613,
      "showtimes": 985,
      "theaters": 260,
      "last_week_ratio": null,
      "day": "1st Thu"
    },
    {
      "title": "Including Independents",
      "date": "26-03-2026",
      "time": "2PM",
      "rank": 7,
      "sales": 7254,
      "seats": 115161,
      "showtimes": 558,
      "theaters": 260,
      "last_week_ratio": null,
      "day": "1st Thu"
    },
    {
      "title": "Including Independents",
      "date": "26-03-2026",
      "time": "Final",
      "rank": 8,
      "sales": 15054,
      "seats": 272117,
      "showtimes": 1250,
      "theaters": 260,
      "last_week_ratio": null,
      "day": "1st Thu"
    },
    {
      "title": "Including Independents",
      "date": "09-04-2026",
      "time": "7PM",
      "rank": 13,
      "sales": 2614,
      "seats": 51309,
      "showtimes": 376,
      "theaters": 259,
      "last_week_ratio": null,
      "day": "3rd Thu"
    },
    {
      "title": "Including Independents",
      "date": "09-04-2026",
      "time": "Final",
      "rank": 12,
      "sales": 3639,
      "seats": 64151,
      "showtimes": 457,
      "theaters": 248,
      "last_week_ratio": null,
      "day": "3rd Thu"
    },
    {
      "title": "Including Independents",
      "date": "19-04-2026",
      "time": "7PM",
      "rank": 15,
      "sales": 2756,
      "seats": 18203,
      "showtimes": 157,
      "theaters": 240,
      "last_week_ratio": null,
      "day": "4th Sun"
    },
    {
      "title": "Including Independents",
      "date": "19-04-2026",
      "time": "2PM",
      "rank": 19,
      "sales": 1218,
      "seats": 7723,
      "showtimes": 66,
      "theaters": 240,
      "last_week_ratio": null,
      "day": "4th Sun"
    },
    {
      "title": "Including Independents",
      "date": "19-04-2026",
      "time": "Final",
      "rank": 17,
      "sales": 2786,
      "seats": 26773,
      "showtimes": 226,
      "theaters": 241,
      "last_week_ratio": null,
      "day": "4th Sun"
    },
    {
      "title": "Including Independents",
      "date": "26-04-2026",
      "time": "Final",
      "rank": 19,
      "sales": 1018,
      "seats": 9095,
      "showtimes": 86,
      "theaters": 92,
      "last_week_ratio": null,
      "day": "5th Sun"
    },
    {
      "title": "Including Independents",
      "date": "29-04-2026",
      "time": "7PM",
      "rank": 19,
      "sales": 1276,
      "seats": 4775,
      "showtimes": 46,
      "theaters": 77,
      "last_week_ratio": 106.8,
      "day": "5th Wed"
    },
    {
      "title": "Including Independents",
      "date": "29-04-2026",
      "time": "2PM",
      "rank": 23,
      "sales": 395,
      "seats": 1152,
      "showtimes": 13,
      "theaters": 77,
      "last_week_ratio": null,
      "day": "5th Wed"
    },
    {
      "title": "Including Independents",
      "date": "29-04-2026",
      "time": "Final",
      "rank": 18,
      "sales": 701,
      "seats": 13249,
      "showtimes": 117,
      "theaters": 123,
      "last_week_ratio": null,
      "day": "5th Wed"
    }
  ]
}