{
  "movie_name": "Uchusenkan Yamato: Kinenban",
  "jp_name": "宇宙戦艦ヤマト 劇場版",
  "releaseDate": "11-12-2023",
  "entries": [
    {
      "title": "Including Independents",
      "date": "11-12-2023",
      "time": "7PM",
      "rank": 18,
      "sales": 812,
      "seats": 8038,
      "showtimes": 50,
      "theaters": 29,
      "last_week_ratio": null,
      "day": "1st Mon"
    },
    {
      "title": "Including Independents",
      "date": "11-12-2023",
      "time": "2PM",
      "rank": 18,
      "sales": 498,
      "seats": 4795,
      "showtimes": 29,
      "theaters": 29,
      "last_week_ratio": null,
      "day": "1st Mon"
    },
    {
      "title": "Including Independents",
      "date": "11-12-2023",
      "time": "Final",
      "rank": 16,
      "sales": 2227,
      "seats": 8500,
      "showtimes": 56,
      "theaters": 29,
      "last_week_ratio": null,
      "day": "1st Mon"
    }
  ]
}