{
  "date": "06-09-2020",
  "times": [
    {
      "title": "Including Independents",
      "time": "2PM",
      "data": [
        {
          "moviename": "Blue, painful, and fragile",
          "japanese name": "青くて痛くて脆い",
          "sales": 4782,
          "seats": 18251,
          "showtimes": 319,
          "theaters": 234,
          "rank": 10,
          "last_week_ratio": null
        },
        {
          "moviename": "Theatrical Version: Secret × Warrior: Phantom Mirage! ~Let’s Turn It into a Movie~",
          "japanese name": "劇場版 ひみつ×戦士 ファントミラージュ！～映画になってちょーだいします～",
          "sales": 493,
          "seats": 1669,
          "showtimes": 19,
          "theaters": 33,
          "rank": 25,
          "last_week_ratio": null
        },
        {
          "moviename": "Interstellar",
          "japanese name": "インターステラー",
          "sales": 2121,
          "seats": 3776,
          "showtimes": 24,
          "theaters": 32,
          "rank": 14,
          "last_week_ratio": null
        },
        {
          "moviename": "Thought, thought, feigned, feigned",
          "japanese name": "思い、思われ、ふり、ふられ",
          "sales": 4255,
          "seats": 10478,
          "showtimes": 189,
          "theaters": 260,
          "rank": 11,
          "last_week_ratio": null
        },
        {
          "moviename": "Starting today, I am!!! The theatrical version",
          "japanese name": "今日から俺は！！劇場版",
          "sales": 12666,
          "seats": 28603,
          "showtimes": 373,
          "theaters": 291,
          "rank": 5,
          "last_week_ratio": null
        },
        {
          "moviename": "Ultraman Tiger Theatrical Movie: New Generation Climax",
          "japanese name": "劇場版ウルトラマンタイガ ニュージェネクライマックス",
          "sales": 1246,
          "seats": 5754,
          "showtimes": 79,
          "theaters": 82,
          "rank": 18,
          "last_week_ratio": null
        },
        {
          "moviename": "Our Lies and Truths: Documentary of AKB48",
          "japanese name": "僕たちの嘘と真実 Ｄｏｃｕｍｅｎｔａｒｙ ｏｆ 欅坂４６",
          "sales": 7534,
          "seats": 21556,
          "showtimes": 162,
          "theaters": 87,
          "rank": 7,
          "last_week_ratio": null
        },
        {
          "moviename": "“Working Cells!!” The most powerful enemy appears once again. The “intestines” are in a complete uproar!",
          "japanese name": "「はたらく細胞！！」最強の敵、再び。体の中は’腸”大騒ぎ！",
          "sales": 6582,
          "seats": 24631,
          "showtimes": 198,
          "theaters": 91,
          "rank": 9,
          "last_week_ratio": null
        },
        {
          "moviename": "Booksmart Graduation Night Party Debut",
          "japanese name": "ブックスマート 卒業前夜のパーティーデビュー",
          "sales": 498,
          "seats": 1450,
          "showtimes": 21,
          "theaters": 24,
          "rank": 24,
          "last_week_ratio": 171.7
        },
        {
          "moviename": "Movie Asshole Land and Others (Toei Manga Matsuri)",
          "japanese name": "映画おしりたんてい・他（東映まんがまつり）",
          "sales": 871,
          "seats": 5652,
          "showtimes": 75,
          "theaters": 81,
          "rank": 20,
          "last_week_ratio": null
        },
        {
          "moviename": "Movie: Given",
          "japanese name": "映画 ギヴン",
          "sales": 1204,
          "seats": 3130,
          "showtimes": 31,
          "theaters": 28,
          "rank": 19,
          "last_week_ratio": null
        },
        {
          "moviename": "Reframe The Theater Experience with You",
          "japanese name": "Ｒｅｆｒａｍｅ ＴＨＥＡＴＥＲ ＥＸＰＥＲＩＥＮＣＥ ｗｉｔｈ ｙｏｕ",
          "sales": 1848,
          "seats": 8945,
          "showtimes": 101,
          "theaters": 59,
          "rank": 15,
          "last_week_ratio": null
        },
        {
          "moviename": "Cute Pedal (Live-action version)",
          "japanese name": "弱虫ペダル（実写版）",
          "sales": 3756,
          "seats": 11248,
          "showtimes": 189,
          "theaters": 292,
          "rank": 13,
          "last_week_ratio": null
        },
        {
          "moviename": "Pavarotti The Tenor of the Sun",
          "japanese name": "パヴァロッティ 太陽のテノール",
          "sales": 1367,
          "seats": 5474,
          "showtimes": 70,
          "theaters": 41,
          "rank": 17,
          "last_week_ratio": null
        },
        {
          "moviename": "Half the magic",
          "japanese name": "２分の１の魔法",
          "sales": 12960,
          "seats": 35195,
          "showtimes": 524,
          "theaters": 299,
          "rank": 4,
          "last_week_ratio": null
        },
        {
          "moviename": "Thread",
          "japanese name": "糸",
          "sales": 14409,
          "seats": 47881,
          "showtimes": 537,
          "theaters": 291,
          "rank": 3,
          "last_week_ratio": null
        },
        {
          "moviename": "Movie Thomas the Tank Engine: Chao! Fly and Sing and Discover!",
          "japanese name": "映画 きかんしゃトーマス チャオ！とんでうたってディスカバリー！！",
          "sales": 4236,
          "seats": 29619,
          "showtimes": 369,
          "theaters": 128,
          "rank": 12,
          "last_week_ratio": null
        },
        {
          "moviename": "Confident Man JP: Princess Edition",
          "japanese name": "コンフィデンスマンＪＰ プリンセス編",
          "sales": 7041,
          "seats": 16621,
          "showtimes": 260,
          "theaters": 288,
          "rank": 8,
          "last_week_ratio": null
        },
        {
          "moviename": "(Family De-Danran Cinema) Dr. Dolittle※Screenings reserved for families with children",
          "japanese name": "（家族ｄｅだんらんシネマ）ドクター・ドリトル※お子様連れ専用上映回",
          "sales": 781,
          "seats": 5663,
          "showtimes": 66,
          "theaters": 33,
          "rank": 21,
          "last_week_ratio": null
        },
        {
          "moviename": "Accident-prone properties with terrifying layouts",
          "japanese name": "事故物件 恐い間取り",
          "sales": 25797,
          "seats": 86494,
          "showtimes": 587,
          "theaters": 291,
          "rank": 2,
          "last_week_ratio": null
        },
        {
          "moviename": "Fatе/stay night Heavens Feel Chapter 3",
          "japanese name": "Ｆａｔｅ／ｓｔａｙ ｎｉｇｈｔ Ｈｅａｖｅｎｓ Ｆｅｅｌ 第三章",
          "sales": 8096,
          "seats": 22034,
          "showtimes": 274,
          "theaters": 168,
          "rank": 6,
          "last_week_ratio": null
        },
        {
          "moviename": "Movie: Doraemon 2020: Nobita’s New Dinosaur",
          "japanese name": "映画ドラえもん ２０２０ のび太の新恐竜",
          "sales": 29796,
          "seats": 63136,
          "showtimes": 635,
          "theaters": 292,
          "rank": 1,
          "last_week_ratio": null
        },
        {
          "moviename": "mid 90s mid nineties",
          "japanese name": "ｍｉｄ９０ｓ ミッドナインティーズ",
          "sales": 673,
          "seats": 1777,
          "showtimes": 23,
          "theaters": 13,
          "rank": 22,
          "last_week_ratio": null
        },
        {
          "moviename": "A town of people",
          "japanese name": "人数の町",
          "sales": 577,
          "seats": 4533,
          "showtimes": 56,
          "theaters": 42,
          "rank": 23,
          "last_week_ratio": null
        },
        {
          "moviename": "The Brightest Roof in the Universe",
          "japanese name": "宇宙でいちばんあかるい屋根",
          "sales": 1674,
          "seats": 13998,
          "showtimes": 208,
          "theaters": 123,
          "rank": 16,
          "last_week_ratio": null
        }
      ]
    },
    {
      "title": "Including Independents",
      "time": "7PM",
      "data": [
        {
          "moviename": "Blue, painful, and fragile",
          "japanese name": "青くて痛くて脆い",
          "sales": 11185,
          "seats": 34921,
          "showtimes": 612,
          "theaters": 234,
          "rank": 9,
          "last_week_ratio": null
        },
        {
          "moviename": "Interstellar",
          "japanese name": "インターステラー",
          "sales": 3154,
          "seats": 5606,
          "showtimes": 38,
          "theaters": 32,
          "rank": 15,
          "last_week_ratio": null
        },
        {
          "moviename": "Thought, thought, feigned, feigned",
          "japanese name": "思い、思われ、ふり、ふられ",
          "sales": 9949,
          "seats": 23550,
          "showtimes": 410,
          "theaters": 260,
          "rank": 10,
          "last_week_ratio": null
        },
        {
          "moviename": "Glambur",
          "japanese name": "ぐらんぶる",
          "sales": 1286,
          "seats": 5920,
          "showtimes": 88,
          "theaters": 151,
          "rank": 20,
          "last_week_ratio": null
        },
        {
          "moviename": "Starting today, I am!!! The theatrical version",
          "japanese name": "今日から俺は！！劇場版",
          "sales": 22427,
          "seats": 54878,
          "showtimes": 702,
          "theaters": 291,
          "rank": 4,
          "last_week_ratio": null
        },
        {
          "moviename": "Ultraman Tiger Theatrical Movie: New Generation Climax",
          "japanese name": "劇場版ウルトラマンタイガ ニュージェネクライマックス",
          "sales": 1301,
          "seats": 6354,
          "showtimes": 87,
          "theaters": 82,
          "rank": 19,
          "last_week_ratio": null
        },
        {
          "moviename": "Our Lies and Truths: Documentary of AKB48",
          "japanese name": "僕たちの嘘と真実 Ｄｏｃｕｍｅｎｔａｒｙ ｏｆ 欅坂４６",
          "sales": 14259,
          "seats": 41971,
          "showtimes": 310,
          "theaters": 87,
          "rank": 8,
          "last_week_ratio": null
        },
        {
          "moviename": "“Working Cells!!” The most powerful enemy appears once again. The “intestines” are in a complete uproar!",
          "japanese name": "「はたらく細胞！！」最強の敵、再び。体の中は’腸”大騒ぎ！",
          "sales": 9681,
          "seats": 45035,
          "showtimes": 362,
          "theaters": 91,
          "rank": 11,
          "last_week_ratio": null
        },
        {
          "moviename": "Movie Asshole Land and Others (Toei Manga Matsuri)",
          "japanese name": "映画おしりたんてい・他（東映まんがまつり）",
          "sales": 922,
          "seats": 6009,
          "showtimes": 81,
          "theaters": 81,
          "rank": 23,
          "last_week_ratio": null
        },
        {
          "moviename": "Movie: Given",
          "japanese name": "映画 ギヴン",
          "sales": 2303,
          "seats": 5266,
          "showtimes": 58,
          "theaters": 28,
          "rank": 17,
          "last_week_ratio": null
        },
        {
          "moviename": "Reframe The Theater Experience with You",
          "japanese name": "Ｒｅｆｒａｍｅ ＴＨＥＡＴＥＲ ＥＸＰＥＲＩＥＮＣＥ ｗｉｔｈ ｙｏｕ",
          "sales": 3191,
          "seats": 17184,
          "showtimes": 192,
          "theaters": 59,
          "rank": 14,
          "last_week_ratio": null
        },
        {
          "moviename": "Hinatazaka 46 Documentary Movie: 3 Years Since Debut",
          "japanese name": "日向坂４６ドキュメンタリー映画 ３年目のデビュー",
          "sales": 870,
          "seats": 2650,
          "showtimes": 37,
          "theaters": 46,
          "rank": 24,
          "last_week_ratio": null
        },
        {
          "moviename": "Cute Pedal (Live-action version)",
          "japanese name": "弱虫ペダル（実写版）",
          "sales": 7102,
          "seats": 25305,
          "showtimes": 398,
          "theaters": 292,
          "rank": 12,
          "last_week_ratio": null
        },
        {
          "moviename": "Pavarotti The Tenor of the Sun",
          "japanese name": "パヴァロッティ 太陽のテノール",
          "sales": 1949,
          "seats": 10128,
          "showtimes": 124,
          "theaters": 41,
          "rank": 18,
          "last_week_ratio": null
        },
        {
          "moviename": "Half the magic",
          "japanese name": "２分の１の魔法",
          "sales": 19670,
          "seats": 56861,
          "showtimes": 847,
          "theaters": 299,
          "rank": 5,
          "last_week_ratio": null
        },
        {
          "moviename": "Thread",
          "japanese name": "糸",
          "sales": 29863,
          "seats": 87345,
          "showtimes": 962,
          "theaters": 291,
          "rank": 3,
          "last_week_ratio": null
        },
        {
          "moviename": "Movie Thomas the Tank Engine: Chao! Fly and Sing and Discover!",
          "japanese name": "映画 きかんしゃトーマス チャオ！とんでうたってディスカバリー！！",
          "sales": 5008,
          "seats": 38052,
          "showtimes": 476,
          "theaters": 128,
          "rank": 13,
          "last_week_ratio": null
        },
        {
          "moviename": "Confident Man JP: Princess Edition",
          "japanese name": "コンフィデンスマンＪＰ プリンセス編",
          "sales": 15007,
          "seats": 34565,
          "showtimes": 534,
          "theaters": 288,
          "rank": 6,
          "last_week_ratio": null
        },
        {
          "moviename": "(Family De-Danran Cinema) Dr. Dolittle※Screenings reserved for families with children",
          "japanese name": "（家族ｄｅだんらんシネマ）ドクター・ドリトル※お子様連れ専用上映回",
          "sales": 1237,
          "seats": 8597,
          "showtimes": 100,
          "theaters": 33,
          "rank": 21,
          "last_week_ratio": null
        },
        {
          "moviename": "Accident-prone properties with terrifying layouts",
          "japanese name": "事故物件 恐い間取り",
          "sales": 56716,
          "seats": 156476,
          "showtimes": 1077,
          "theaters": 291,
          "rank": 1,
          "last_week_ratio": null
        },
        {
          "moviename": "Fatе/stay night Heavens Feel Chapter 3",
          "japanese name": "Ｆａｔｅ／ｓｔａｙ ｎｉｇｈｔ Ｈｅａｖｅｎｓ Ｆｅｅｌ 第三章",
          "sales": 14540,
          "seats": 42270,
          "showtimes": 525,
          "theaters": 168,
          "rank": 7,
          "last_week_ratio": null
        },
        {
          "moviename": "Movie: Doraemon 2020: Nobita’s New Dinosaur",
          "japanese name": "映画ドラえもん ２０２０ のび太の新恐竜",
          "sales": 41822,
          "seats": 92432,
          "showtimes": 942,
          "theaters": 292,
          "rank": 2,
          "last_week_ratio": null
        },
        {
          "moviename": "mid 90s mid nineties",
          "japanese name": "ｍｉｄ９０ｓ ミッドナインティーズ",
          "sales": 1101,
          "seats": 3327,
          "showtimes": 38,
          "theaters": 13,
          "rank": 22,
          "last_week_ratio": null
        },
        {
          "moviename": "A town of people",
          "japanese name": "人数の町",
          "sales": 867,
          "seats": 7110,
          "showtimes": 88,
          "theaters": 42,
          "rank": 25,
          "last_week_ratio": null
        },
        {
          "moviename": "The Brightest Roof in the Universe",
          "japanese name": "宇宙でいちばんあかるい屋根",
          "sales": 2494,
          "seats": 24533,
          "showtimes": 359,
          "theaters": 123,
          "rank": 16,
          "last_week_ratio": null
        }
      ]
    },
    {
      "title": "Including Independents",
      "time": "Final",
      "data": [
        {
          "moviename": "Blue, painful, and fragile",
          "japanese name": "青くて痛くて脆い",
          "sales": 12108,
          "seats": 45560,
          "showtimes": 788,
          "theaters": 234,
          "rank": 9,
          "last_week_ratio": null
        },
        {
          "moviename": "Interstellar",
          "japanese name": "インターステラー",
          "sales": 3891,
          "seats": 9156,
          "showtimes": 62,
          "theaters": 32,
          "rank": 14,
          "last_week_ratio": null
        },
        {
          "moviename": "Thought, thought, feigned, feigned",
          "japanese name": "思い、思われ、ふり、ふられ",
          "sales": 10574,
          "seats": 30155,
          "showtimes": 511,
          "theaters": 260,
          "rank": 10,
          "last_week_ratio": null
        },
        {
          "moviename": "Glambur",
          "japanese name": "ぐらんぶる",
          "sales": 1536,
          "seats": 8931,
          "showtimes": 136,
          "theaters": 151,
          "rank": 19,
          "last_week_ratio": null
        },
        {
          "moviename": "Starting today, I am!!! The theatrical version",
          "japanese name": "今日から俺は！！劇場版",
          "sales": 23419,
          "seats": 68808,
          "showtimes": 879,
          "theaters": 291,
          "rank": 4,
          "last_week_ratio": null
        },
        {
          "moviename": "Ultraman Tiger Theatrical Movie: New Generation Climax",
          "japanese name": "劇場版ウルトラマンタイガ ニュージェネクライマックス",
          "sales": 1348,
          "seats": 6507,
          "showtimes": 89,
          "theaters": 82,
          "rank": 21,
          "last_week_ratio": null
        },
        {
          "moviename": "Our Lies and Truths: Documentary of AKB48",
          "japanese name": "僕たちの嘘と真実 Ｄｏｃｕｍｅｎｔａｒｙ ｏｆ 欅坂４６",
          "sales": 15616,
          "seats": 53241,
          "showtimes": 386,
          "theaters": 87,
          "rank": 8,
          "last_week_ratio": null
        },
        {
          "moviename": "“Working Cells!!” The most powerful enemy appears once again. The “intestines” are in a complete uproar!",
          "japanese name": "「はたらく細胞！！」最強の敵、再び。体の中は’腸”大騒ぎ！",
          "sales": 10056,
          "seats": 55541,
          "showtimes": 443,
          "theaters": 91,
          "rank": 11,
          "last_week_ratio": null
        },
        {
          "moviename": "Booksmart Graduation Night Party Debut",
          "japanese name": "ブックスマート 卒業前夜のパーティーデビュー",
          "sales": 971,
          "seats": 3939,
          "showtimes": 63,
          "theaters": 24,
          "rank": 24,
          "last_week_ratio": 135.6
        },
        {
          "moviename": "Movie: Given",
          "japanese name": "映画 ギヴン",
          "sales": 2744,
          "seats": 7060,
          "showtimes": 78,
          "theaters": 28,
          "rank": 16,
          "last_week_ratio": null
        },
        {
          "moviename": "Reframe The Theater Experience with You",
          "japanese name": "Ｒｅｆｒａｍｅ ＴＨＥＡＴＥＲ ＥＸＰＥＲＩＥＮＣＥ ｗｉｔｈ ｙｏｕ",
          "sales": 3418,
          "seats": 22457,
          "showtimes": 251,
          "theaters": 59,
          "rank": 15,
          "last_week_ratio": null
        },
        {
          "moviename": "Hinatazaka 46 Documentary Movie: 3 Years Since Debut",
          "japanese name": "日向坂４６ドキュメンタリー映画 ３年目のデビュー",
          "sales": 1056,
          "seats": 4576,
          "showtimes": 57,
          "theaters": 46,
          "rank": 23,
          "last_week_ratio": null
        },
        {
          "moviename": "Cute Pedal (Live-action version)",
          "japanese name": "弱虫ペダル（実写版）",
          "sales": 7478,
          "seats": 32734,
          "showtimes": 507,
          "theaters": 292,
          "rank": 12,
          "last_week_ratio": null
        },
        {
          "moviename": "Pavarotti The Tenor of the Sun",
          "japanese name": "パヴァロッティ 太陽のテノール",
          "sales": 2015,
          "seats": 12235,
          "showtimes": 151,
          "theaters": 41,
          "rank": 18,
          "last_week_ratio": null
        },
        {
          "moviename": "Half the magic",
          "japanese name": "２分の１の魔法",
          "sales": 20106,
          "seats": 63732,
          "showtimes": 954,
          "theaters": 299,
          "rank": 5,
          "last_week_ratio": null
        },
        {
          "moviename": "Thread",
          "japanese name": "糸",
          "sales": 31994,
          "seats": 107242,
          "showtimes": 1173,
          "theaters": 291,
          "rank": 3,
          "last_week_ratio": null
        },
        {
          "moviename": "Movie Thomas the Tank Engine: Chao! Fly and Sing and Discover!",
          "japanese name": "映画 きかんしゃトーマス チャオ！とんでうたってディスカバリー！！",
          "sales": 5008,
          "seats": 38586,
          "showtimes": 481,
          "theaters": 128,
          "rank": 13,
          "last_week_ratio": null
        },
        {
          "moviename": "Confident Man JP: Princess Edition",
          "japanese name": "コンフィデンスマンＪＰ プリンセス編",
          "sales": 16310,
          "seats": 47344,
          "showtimes": 720,
          "theaters": 288,
          "rank": 6,
          "last_week_ratio": null
        },
        {
          "moviename": "(Family De-Danran Cinema) Dr. Dolittle※Screenings reserved for families with children",
          "japanese name": "（家族ｄｅだんらんシネマ）ドクター・ドリトル※お子様連れ専用上映回",
          "sales": 1233,
          "seats": 8830,
          "showtimes": 102,
          "theaters": 33,
          "rank": 22,
          "last_week_ratio": null
        },
        {
          "moviename": "Accident-prone properties with terrifying layouts",
          "japanese name": "事故物件 恐い間取り",
          "sales": 62114,
          "seats": 195310,
          "showtimes": 1344,
          "theaters": 291,
          "rank": 1,
          "last_week_ratio": null
        },
        {
          "moviename": "Fatе/stay night Heavens Feel Chapter 3",
          "japanese name": "Ｆａｔｅ／ｓｔａｙ ｎｉｇｈｔ Ｈｅａｖｅｎｓ Ｆｅｅｌ 第三章",
          "sales": 16043,
          "seats": 55005,
          "showtimes": 686,
          "theaters": 168,
          "rank": 7,
          "last_week_ratio": null
        },
        {
          "moviename": "Movie: Doraemon 2020: Nobita’s New Dinosaur",
          "japanese name": "映画ドラえもん ２０２０ のび太の新恐竜",
          "sales": 41740,
          "seats": 93178,
          "showtimes": 953,
          "theaters": 292,
          "rank": 2,
          "last_week_ratio": null
        },
        {
          "moviename": "mid 90s mid nineties",
          "japanese name": "ｍｉｄ９０ｓ ミッドナインティーズ",
          "sales": 1375,
          "seats": 4213,
          "showtimes": 48,
          "theaters": 13,
          "rank": 20,
          "last_week_ratio": null
        },
        {
          "moviename": "A town of people",
          "japanese name": "人数の町",
          "sales": 935,
          "seats": 8997,
          "showtimes": 115,
          "theaters": 42,
          "rank": 25,
          "last_week_ratio": null
        },
        {
          "moviename": "The Brightest Roof in the Universe",
          "japanese name": "宇宙でいちばんあかるい屋根",
          "sales": 2617,
          "seats": 30354,
          "showtimes": 438,
          "theaters": 123,
          "rank": 17,
          "last_week_ratio": null
        }
      ]
    }
  ]
}